gmscloud/__init__.py
gmscloud/do_print_utils.py
gmscloud/get_app_info.py
gmscloud/get_base_url.py
gmscloud/konversi_tanggal_utils.py
gmscloud/main.py
gmscloud/print_faktur_group_tanda_tangan_utils.py
gmscloud/print_faktur_group_utils.py
gmscloud/print_faktur_rekening_tanda_tangan_utils.py
gmscloud/print_faktur_rekening_utils.py
gmscloud/print_gaji_utils.py
gmscloud/print_surat_jalan_harga_driver_utils.py
gmscloud/print_surat_jalan_harga_ttbk_utils.py
gmscloud/print_surat_jalan_harga_utils.py
gmscloud/print_surat_jalan_no_tabung_utils.py
gmscloud/print_surat_jalan_ttbk_utils.py
gmscloud/print_surat_jalan_utils.py
gmscloud/print_titipan_utils.py
gmscloud/print_ttbk_utils.py
gmscloud/print_ttd_utils.py
gmscloud-2.8.dist-info/licenses/LICENSE.txt
gmscloud-2.8.dist-info/METADATA
gmscloud-2.8.dist-info/WHEEL
gmscloud-2.8.dist-info/entry_points.txt
gmscloud-2.8.dist-info/top_level.txt
gmscloud-2.8.dist-info/RECORD
