Metadata-Version: 2.4
Name: gmscloud
Version: 2.8
Summary: Aplikasi Print Dokumen
Author-email: Fikri Hidayat <fhidayat2206@gmail.com>
License: MIT
Requires-Python: >=3.9
License-File: LICENSE.txt
Requires-Dist: pywin32
Requires-Dist: beautifultable
Requires-Dist: requests
Dynamic: license-file
